{"state":"maharashtra","stateLabel":"Maharashtra","district":"Aurangabad","districtSlug":"aurangabad","latestQuarter":"2025-12","indicators":{"credit_deposit_ratio":{"label":"Credit-Deposit Ratio","unit":"%","latest":{"quarter":"2025-12","value":"90.25","field":"overall_cd_ratio"},"series":[{"quarter":"2025-06","value":"88.65","field":"overall_cd_ratio"},{"quarter":"2025-09","value":"88.88","field":"overall_cd_ratio"},{"quarter":"2025-12","value":"90.25","field":"overall_cd_ratio"}]},"branch_network":{"label":"Bank Branches","unit":"","latest":{"quarter":"2025-12","value":"521","field":"total_branch"},"series":[{"quarter":"2025-06","value":"519","field":"total_branch"},{"quarter":"2025-09","value":"513","field":"total_branch"},{"quarter":"2025-12","value":"521","field":"total_branch"}]},"kcc":{"label":"KCC Cards Issued","unit":"","latest":{"quarter":"2025-09","value":"336406","field":"total_no_of_kcc"},"series":[{"quarter":"2025-09","value":"336406","field":"total_no_of_kcc"}]},"shg":{"label":"SHGs Savings-Linked","unit":"","latest":{"quarter":"2025-12","value":"11199","field":"savings_linked_no"},"series":[{"quarter":"2025-06","value":"11698","field":"savings_linked_no"},{"quarter":"2025-09","value":"1218","field":"savings_linked_no"},{"quarter":"2025-12","value":"11199","field":"savings_linked_no"}]},"social_security":{"label":"Social Security Enrolment","unit":"","latest":{"quarter":"2025-12","value":"1476000","field":"enrolment_under_pmsby"},"series":[{"quarter":"2025-06","value":"1351000","field":"enrolment_under_pmsby"},{"quarter":"2025-09","value":"1403000","field":"enrolment_under_pmsby"},{"quarter":"2025-12","value":"1476000","field":"enrolment_under_pmsby"}]},"viirs_nightlights":{"label":"Nightlight Intensity","unit":"","latest":{"quarter":"2023-12","value":1.2211,"field":"nl_mean"},"series":[{"quarter":"2014-12","value":0.4547,"field":"nl_mean"},{"quarter":"2015-12","value":0.5016,"field":"nl_mean"},{"quarter":"2016-12","value":0.5554,"field":"nl_mean"},{"quarter":"2017-12","value":0.6236,"field":"nl_mean"},{"quarter":"2018-12","value":0.7383,"field":"nl_mean"},{"quarter":"2019-12","value":0.8195,"field":"nl_mean"},{"quarter":"2020-12","value":0.8842,"field":"nl_mean"},{"quarter":"2021-12","value":0.8697,"field":"nl_mean"},{"quarter":"2022-12","value":1.1504,"field":"nl_mean"},{"quarter":"2023-12","value":1.2211,"field":"nl_mean"}]}}}