{"state":"punjab","stateLabel":"Punjab","district":"Firozepur","districtSlug":"firozepur","latestQuarter":"2024-03","indicators":{"digital_transactions":{"label":"UPI Txns (PhonePe)","unit":"","latest":{"quarter":"2024-03","value":"2984805","field":"transaction_count"},"series":[{"quarter":"2020-06","value":"267749","field":"transaction_count"},{"quarter":"2020-09","value":"312560","field":"transaction_count"},{"quarter":"2020-12","value":"343064","field":"transaction_count"},{"quarter":"2021-03","value":"461706","field":"transaction_count"},{"quarter":"2021-06","value":"447201","field":"transaction_count"},{"quarter":"2021-09","value":"566212","field":"transaction_count"},{"quarter":"2021-12","value":"726158","field":"transaction_count"},{"quarter":"2022-03","value":"873797","field":"transaction_count"},{"quarter":"2022-06","value":"970466","field":"transaction_count"},{"quarter":"2022-09","value":"1194856","field":"transaction_count"},{"quarter":"2022-12","value":"1258324","field":"transaction_count"},{"quarter":"2023-03","value":"1446886","field":"transaction_count"},{"quarter":"2023-06","value":"2066667","field":"transaction_count"},{"quarter":"2023-09","value":"2527606","field":"transaction_count"},{"quarter":"2023-12","value":"2748903","field":"transaction_count"},{"quarter":"2024-03","value":"2984805","field":"transaction_count"}]}}}