{"state":"himachal-pradesh","stateLabel":"Himachal Pradesh","district":"Sirmaur","districtSlug":"sirmaur","latestQuarter":"2025-12","indicators":{"credit_deposit_ratio":{"label":"Credit-Deposit Ratio","unit":"%","latest":{"quarter":"2025-12","value":76.68878259136046,"field":"overall_cd_ratio"},"series":[{"quarter":"2025-12","value":76.68878259136046,"field":"overall_cd_ratio"}]},"pmjdy":{"label":"PMJDY Accounts","unit":"","latest":{"quarter":"2025-12","value":153586.0,"field":"total_pmjdy_no"},"series":[{"quarter":"2025-12","value":153586.0,"field":"total_pmjdy_no"}]},"branch_network":{"label":"Bank Branches","unit":"","latest":{"quarter":"2025-12","value":155.0,"field":"total_branch"},"series":[{"quarter":"2025-12","value":155.0,"field":"total_branch"}]},"kcc":{"label":"KCC Cards Issued","unit":"","latest":{"quarter":"2025-12","value":32927.0,"field":"total_no_of_kcc"},"series":[{"quarter":"2025-12","value":32927.0,"field":"total_no_of_kcc"}]},"shg":{"label":"SHGs Savings-Linked","unit":"","latest":{"quarter":"2025-12","value":37.0,"field":"savings_linked_no"},"series":[{"quarter":"2025-12","value":37.0,"field":"savings_linked_no"}]},"digital_transactions":{"label":"UPI Txns (PhonePe)","unit":"","latest":{"quarter":"2024-03","value":"3052172","field":"transaction_count"},"series":[{"quarter":"2020-06","value":"240485","field":"transaction_count"},{"quarter":"2020-09","value":"281385","field":"transaction_count"},{"quarter":"2020-12","value":"327646","field":"transaction_count"},{"quarter":"2021-03","value":"443100","field":"transaction_count"},{"quarter":"2021-06","value":"451501","field":"transaction_count"},{"quarter":"2021-09","value":"567339","field":"transaction_count"},{"quarter":"2021-12","value":"681413","field":"transaction_count"},{"quarter":"2022-03","value":"847647","field":"transaction_count"},{"quarter":"2022-06","value":"962227","field":"transaction_count"},{"quarter":"2022-09","value":"1196118","field":"transaction_count"},{"quarter":"2022-12","value":"1266132","field":"transaction_count"},{"quarter":"2023-03","value":"1454224","field":"transaction_count"},{"quarter":"2023-06","value":"2191815","field":"transaction_count"},{"quarter":"2023-09","value":"2641707","field":"transaction_count"},{"quarter":"2023-12","value":"2744752","field":"transaction_count"},{"quarter":"2024-03","value":"3052172","field":"transaction_count"}]},"aadhaar_authentication":{"label":"Aadhaar-Seeded CASA","unit":"","latest":{"quarter":"2025-12","value":136331.0,"field":"no_of_aadhaar_seeded_casa"},"series":[{"quarter":"2025-12","value":136331.0,"field":"no_of_aadhaar_seeded_casa"}]},"viirs_nightlights":{"label":"Nightlight Intensity","unit":"","latest":{"quarter":"2023-12","value":0.37,"field":"nl_mean"},"series":[{"quarter":"2014-12","value":0.2377,"field":"nl_mean"},{"quarter":"2015-12","value":0.2307,"field":"nl_mean"},{"quarter":"2016-12","value":0.2011,"field":"nl_mean"},{"quarter":"2017-12","value":0.2646,"field":"nl_mean"},{"quarter":"2018-12","value":0.2617,"field":"nl_mean"},{"quarter":"2019-12","value":0.2577,"field":"nl_mean"},{"quarter":"2020-12","value":0.25,"field":"nl_mean"},{"quarter":"2021-12","value":0.2725,"field":"nl_mean"},{"quarter":"2022-12","value":0.3254,"field":"nl_mean"},{"quarter":"2023-12","value":0.37,"field":"nl_mean"}]}},"polygon":{"path":"M459.0,24.0L488.2,45.5L495.6,43.7L513.7,61.3L517.2,91.5L494.8,105.7L512.3,141.0L510.1,153.5L524.3,164.3L548.7,162.9L560.0,182.5L560.9,224.6L586.3,233.0L594.0,220.6L610.5,220.0L609.1,243.2L656.7,238.7L663.7,228.4L674.1,225.6L678.0,211.5L705.3,217.7L709.1,214.3L710.4,220.2L715.4,218.1L730.2,228.8L731.5,239.6L748.7,252.3L753.3,262.6L749.8,271.2L774.8,277.8L777.8,287.8L794.9,303.1L787.0,314.2L787.4,327.1L827.5,345.9L817.5,356.6L825.8,367.9L821.8,376.4L830.8,386.0L808.5,383.5L809.0,400.9L786.3,394.6L783.4,403.6L795.6,410.9L811.1,435.6L819.6,433.8L828.9,439.7L850.0,432.7L858.9,459.4L851.8,465.6L850.1,480.8L819.1,486.5L780.3,508.3L763.9,511.0L736.6,533.2L703.0,533.2L694.9,547.6L676.6,545.0L651.6,552.2L631.9,566.1L642.8,588.9L639.1,596.0L609.1,579.4L585.1,535.5L570.2,549.3L566.4,570.7L561.3,565.5L544.0,575.0L518.9,579.4L512.9,572.3L499.0,572.2L499.8,566.3L518.7,559.3L526.6,545.9L533.4,545.1L537.5,531.4L531.1,524.2L510.6,546.7L494.1,553.3L487.1,567.2L477.5,560.4L486.1,550.3L471.0,547.7L467.6,538.5L449.5,538.3L446.6,545.3L437.4,521.9L418.8,524.6L408.5,533.1L397.5,532.2L381.8,522.0L366.9,523.6L359.0,507.6L325.9,499.9L312.9,515.1L309.0,502.3L312.5,490.2L296.5,466.9L252.3,454.6L231.3,431.0L246.1,425.7L247.7,417.6L254.9,418.8L277.6,397.6L275.5,373.6L280.4,365.2L268.1,352.9L272.9,336.3L265.8,325.3L271.8,323.5L237.7,299.7L233.7,289.9L224.2,293.1L224.6,283.8L206.3,271.6L183.6,272.8L165.1,262.2L160.1,264.6L163.7,272.5L147.2,276.5L141.1,272.4L152.8,252.0L197.6,227.0L201.2,193.3L216.6,190.8L226.5,181.5L225.1,174.8L259.6,170.1L273.5,183.0L289.4,175.2L285.7,166.7L313.0,150.5L305.9,141.4L315.9,135.8L314.2,130.0L328.4,130.9L356.8,104.6L358.8,95.6L388.1,84.5L391.1,71.5L409.8,62.1L422.0,44.0L451.6,37.7L459.0,24.0Z","viewBox":"0 0 1000 620"}}