{"indicator":"credit_deposit_ratio","quarter":"2019-12","label":"December 2019","districts":[{"district":"24 Paraganas South","state":"west-bengal","overall_cd_ratio":"45.88","total_advance":"16335.87"},{"district":"Ahmadabad","state":"gujarat","overall_cd_ratio":"116.27","total_deposit":"20011212.71","total_advance":"23267554.85","total_branch":"1500"},{"district":"Alipurduar","state":"west-bengal","overall_cd_ratio":"40.88","total_advance":"1998.4"},{"district":"Ambala","state":"haryana","overall_cd_ratio":"41.42","total_deposit":"2194302.0","total_advance":"908851.0"},{"district":"Amreli","state":"gujarat","overall_cd_ratio":"75.64","total_deposit":"806685.44","total_advance":"610171.2","total_branch":"259"},{"district":"Anand","state":"gujarat","overall_cd_ratio":"27.06","total_deposit":"3167146.58","total_advance":"857128.46","total_branch":"409"},{"district":"Arvalli","state":"gujarat","overall_cd_ratio":"70.23","total_deposit":"372707.95","total_advance":"261744.56","total_branch":"139"},{"district":"Baksa","state":"assam","overall_cd_ratio":"50.39"},{"district":"Banas Kantha","state":"gujarat","overall_cd_ratio":"98.97","total_deposit":"1037750.93","total_advance":"1027034.02","total_branch":"354"},{"district":"Bankura","state":"west-bengal","overall_cd_ratio":"42.14","total_advance":"4202.5"},{"district":"Barpeta","state":"assam","overall_cd_ratio":"64.25"},{"district":"Bharuch","state":"gujarat","overall_cd_ratio":"81.48","total_deposit":"2003012.2","total_advance":"1632052.9","total_branch":"320"},{"district":"Bhavnagar","state":"gujarat","overall_cd_ratio":"59.94","total_deposit":"1733329.45","total_advance":"1039016.44","total_branch":"317"},{"district":"Bhiwani","state":"haryana","overall_cd_ratio":"70.18","total_deposit":"830798.0","total_advance":"583081.0"},{"district":"Birbhum","state":"west-bengal","overall_cd_ratio":"40.07","total_advance":"5991.76"},{"district":"Bishnupur","state":"manipur","overall_cd_ratio":"101"},{"district":"Biswanath","state":"assam","overall_cd_ratio":"48.41"},{"district":"Bongaigaon","state":"assam","overall_cd_ratio":"53.6"},{"district":"Botad","state":"gujarat","overall_cd_ratio":"82.37","total_deposit":"230217.32","total_advance":"189628.13","total_branch":"78"},{"district":"Cachar","state":"assam","overall_cd_ratio":"41.11"},{"district":"Chandel","state":"manipur","overall_cd_ratio":"89"},{"district":"Charaideo","state":"assam","overall_cd_ratio":"45.71"},{"district":"Charki Dadri","state":"haryana","overall_cd_ratio":"55.29","total_deposit":"330297.0","total_advance":"182609.0"},{"district":"Chhotaudepur","state":"gujarat","overall_cd_ratio":"53.24","total_deposit":"253393.82","total_advance":"134896.12","total_branch":"94"},{"district":"Chirang","state":"assam","overall_cd_ratio":"43.71"},{"district":"Chittoor","state":"andhra-pradesh","overall_cd_ratio":"70.27"},{"district":"Churachandpur","state":"manipur","overall_cd_ratio":"64"},{"district":"Coochbehar","state":"west-bengal","overall_cd_ratio":"68.36","total_advance":"5415.81"},{"district":"Dang","state":"gujarat","overall_cd_ratio":"12.52","total_deposit":"71865.88","total_advance":"9000.61","total_branch":"17"},{"district":"Darjeeling","state":"west-bengal","overall_cd_ratio":"59.87","total_advance":"10549.83"},{"district":"Darrang","state":"assam","overall_cd_ratio":"61.94"},{"district":"Dhalai","state":"tripura","overall_cd_ratio":"94.0","total_deposit":"102611.89","total_advance":"95973.59","total_branch":"46.0"},{"district":"Dhemaji","state":"assam","overall_cd_ratio":"68.71"},{"district":"Dhubri","state":"assam","overall_cd_ratio":"56.62"},{"district":"Dibrugarh","state":"assam","overall_cd_ratio":"45.89"},{"district":"Dima Hasao","state":"assam","overall_cd_ratio":"33.44"},{"district":"Dohad","state":"gujarat","overall_cd_ratio":"45.61","total_deposit":"443946.96","total_advance":"202503.67","total_branch":"123"},{"district":"East Godavari","state":"andhra-pradesh","overall_cd_ratio":"128.27"},{"district":"Faridabad","state":"haryana","overall_cd_ratio":"69.46","total_deposit":"3775188.0","total_advance":"2622296.0"},{"district":"Fatehabad","state":"haryana","overall_cd_ratio":"100.25","total_deposit":"625812.0","total_advance":"627378.0"},{"district":"Gandhinagar","state":"gujarat","overall_cd_ratio":"59.31","total_deposit":"3322099.68","total_advance":"1970183.43","total_branch":"342"},{"district":"Gir Somnath","state":"gujarat","overall_cd_ratio":"49.62","total_deposit":"566732.95","total_advance":"281212.99","total_branch":"122"},{"district":"Goalpara","state":"assam","overall_cd_ratio":"49.06"},{"district":"Golaghat","state":"assam","overall_cd_ratio":"73.48"},{"district":"Gomati","state":"tripura","overall_cd_ratio":"70.0","total_deposit":"173812.75","total_advance":"121809.84","total_branch":"64.0"},{"district":"Guntur","state":"andhra-pradesh","overall_cd_ratio":"141.88"},{"district":"Gurugram","state":"haryana","overall_cd_ratio":"59.75","total_deposit":"14565281.0","total_advance":"8702597.0"},{"district":"Hailakandi","state":"assam","overall_cd_ratio":"37.53"},{"district":"Hisar","state":"haryana","overall_cd_ratio":"88.01","total_deposit":"1620927.0","total_advance":"1426515.0"},{"district":"Hojai","state":"assam","overall_cd_ratio":"38.27"},{"district":"Hooghly","state":"west-bengal","overall_cd_ratio":"28.08","total_advance":"10624.55"},{"district":"Howrah","state":"west-bengal","overall_cd_ratio":"42.8","total_advance":"16249.91"},{"district":"Imphal East","state":"manipur","overall_cd_ratio":"69"},{"district":"Imphal West","state":"manipur","overall_cd_ratio":"61"},{"district":"Jalpaiguri","state":"west-bengal","overall_cd_ratio":"43.88","total_advance":"3469.2"},{"district":"Jamnagar","state":"gujarat","overall_cd_ratio":"82.88","total_deposit":"1597467.87","total_advance":"1323969.57","total_branch":"264"},{"district":"Jhajjar","state":"haryana","overall_cd_ratio":"46.04","total_deposit":"1095617.0","total_advance":"504406.0"},{"district":"Jhargram","state":"west-bengal","overall_cd_ratio":"41.01","total_advance":"1491.82"},{"district":"Jind","state":"haryana","overall_cd_ratio":"83.41","total_deposit":"772817.0","total_advance":"644605.0"},{"district":"Jiribam","state":"manipur","overall_cd_ratio":"99"},{"district":"Jorhat","state":"assam","overall_cd_ratio":"57.33"},{"district":"Junagadh","state":"gujarat","overall_cd_ratio":"52.12","total_deposit":"1307217.69","total_advance":"681367.25","total_branch":"244"},{"district":"Kachchh","state":"gujarat","overall_cd_ratio":"41.46","total_deposit":"3783885.45","total_advance":"1568892","total_branch":"417"},{"district":"Kaithal","state":"haryana","overall_cd_ratio":"107.04","total_deposit":"642449.0","total_advance":"687668.0"},{"district":"Kakching","state":"manipur","overall_cd_ratio":"156"},{"district":"Kalimpong","state":"west-bengal","overall_cd_ratio":"35.4","total_advance":"501.98"},{"district":"Kamjong","state":"manipur","overall_cd_ratio":"223"},{"district":"Kamrup","state":"assam","overall_cd_ratio":"72.51"},{"district":"Kamrup Metro","state":"assam","overall_cd_ratio":"71.51"},{"district":"Kangpokpi","state":"manipur","overall_cd_ratio":"96"},{"district":"Karbi Anglong","state":"assam","overall_cd_ratio":"50"},{"district":"Karimganj","state":"assam","overall_cd_ratio":"34.04"},{"district":"Karnal","state":"haryana","overall_cd_ratio":"126.43","total_deposit":"1669788.0","total_advance":"2111081.0"},{"district":"Kheda","state":"gujarat","overall_cd_ratio":"38.09","total_deposit":"1547449.81","total_advance":"589430.96","total_branch":"299"},{"district":"Khowai","state":"tripura","overall_cd_ratio":"67.0","total_deposit":"118228.4","total_advance":"79057.49","total_branch":"38.0"},{"district":"Kokrajhar","state":"assam","overall_cd_ratio":"32.33"},{"district":"Kolkata","state":"west-bengal","overall_cd_ratio":"78.32","total_advance":"252889.87"},{"district":"Krishna","state":"andhra-pradesh","overall_cd_ratio":"151.34"},{"district":"Kurnool","state":"andhra-pradesh","overall_cd_ratio":"120.35"},{"district":"Kurukshetra","state":"haryana","overall_cd_ratio":"64.83","total_deposit":"1167829.0","total_advance":"757141.0"},{"district":"Lakhimpur","state":"assam","overall_cd_ratio":"72.55"},{"district":"Mahendragarh","state":"haryana","overall_cd_ratio":"45.57","total_deposit":"707226.0","total_advance":"322317.0"},{"district":"Mahesana","state":"gujarat","overall_cd_ratio":"80.57","total_deposit":"1610383.54","total_advance":"1297416.28","total_branch":"393"},{"district":"Mahisagar","state":"gujarat","overall_cd_ratio":"35.42","total_deposit":"357553.87","total_advance":"126663.41","total_branch":"92"},{"district":"Majuli","state":"assam","overall_cd_ratio":"51.15"},{"district":"Morbi","state":"gujarat","overall_cd_ratio":"162.84","total_deposit":"851005.13","total_advance":"1385811.6","total_branch":"162"},{"district":"Murshidabad","state":"west-bengal","overall_cd_ratio":"55.36","total_advance":"8713.29"},{"district":"Nadia","state":"west-bengal","overall_cd_ratio":"49.1","total_advance":"13842.47"},{"district":"Nagaon","state":"assam","overall_cd_ratio":"66.6"},{"district":"Nalbari","state":"assam","overall_cd_ratio":"56.98"},{"district":"Navsari","state":"gujarat","overall_cd_ratio":"25.52","total_deposit":"2105808.54","total_advance":"537361.44","total_branch":"284"},{"district":"Noney","state":"manipur","overall_cd_ratio":"125"},{"district":"North Tripura","state":"tripura","overall_cd_ratio":"53.0","total_deposit":"141633.11","total_advance":"75611.94","total_branch":"48.0"},{"district":"Nuh","state":"haryana","overall_cd_ratio":"70.46","total_deposit":"248232.0","total_advance":"174916.0"},{"district":"Palwal","state":"haryana","overall_cd_ratio":"73.81","total_deposit":"574913.0","total_advance":"424347.0"},{"district":"Panch Mahals","state":"gujarat","overall_cd_ratio":"48.78","total_deposit":"651013.8","total_advance":"317541.07","total_branch":"178"},{"district":"Panchkula","state":"haryana","overall_cd_ratio":"90.11","total_deposit":"2600648.0","total_advance":"2343435.0"},{"district":"Panipat","state":"haryana","overall_cd_ratio":"106.43","total_deposit":"1348900.0","total_advance":"1435628.0"},{"district":"Paschim Bardhaman","state":"west-bengal","overall_cd_ratio":"34.75","total_advance":"13760.78"},{"district":"Patan","state":"gujarat","overall_cd_ratio":"70.12","total_deposit":"561448.8","total_advance":"393692.67","total_branch":"173"},{"district":"Pherzawl","state":"manipur","overall_cd_ratio":"841"},{"district":"Porbandar","state":"gujarat","overall_cd_ratio":"33.2","total_deposit":"845641.69","total_advance":"280714.89","total_branch":"94"},{"district":"Prakasam","state":"andhra-pradesh","overall_cd_ratio":"161.0"},{"district":"Purba Bardhaman","state":"west-bengal","overall_cd_ratio":"42.5","total_advance":"10522.27"},{"district":"Purulia","state":"west-bengal","overall_cd_ratio":"45.9","total_advance":"3625.0"},{"district":"Rajkot","state":"gujarat","overall_cd_ratio":"100.32","total_deposit":"4856610.47","total_advance":"4872360.6","total_branch":"658"},{"district":"Rewari","state":"haryana","overall_cd_ratio":"39.1","total_deposit":"1347716.0","total_advance":"526949.0"},{"district":"Rohtak","state":"haryana","overall_cd_ratio":"49.46","total_deposit":"1818116.0","total_advance":"899244.0"},{"district":"Sabar Kantha","state":"gujarat","overall_cd_ratio":"93.37","total_deposit":"823469.45","total_advance":"768852.16","total_branch":"292"},{"district":"Senapati","state":"manipur","overall_cd_ratio":"82"},{"district":"Sepahijala","state":"tripura","overall_cd_ratio":"73.0","total_deposit":"156896.07","total_advance":"114978.0","total_branch":"60.0"},{"district":"Sirsa","state":"haryana","overall_cd_ratio":"99.34","total_deposit":"868809.0","total_advance":"863034.0"},{"district":"Sivasagar","state":"assam","overall_cd_ratio":"56.73"},{"district":"Sonipat","state":"haryana","overall_cd_ratio":"51.55","total_deposit":"1903006.0","total_advance":"980924.0"},{"district":"Sonitpur","state":"assam","overall_cd_ratio":"59.17"},{"district":"South Tripura","state":"tripura","overall_cd_ratio":"60.0","total_deposit":"176782.56","total_advance":"105640.05","total_branch":"59.0"},{"district":"Spsr Nellore","state":"andhra-pradesh","overall_cd_ratio":"144.94"},{"district":"Srikakulam","state":"andhra-pradesh","overall_cd_ratio":"98.7"},{"district":"Surat","state":"gujarat","overall_cd_ratio":"110.82","total_deposit":"7589616.95","total_advance":"8410794.28","total_branch":"890"},{"district":"Surendranagar","state":"gujarat","overall_cd_ratio":"72.12","total_deposit":"840153.41","total_advance":"605940.15","total_branch":"204"},{"district":"Tamenglong","state":"manipur","overall_cd_ratio":"37"},{"district":"Tapi","state":"gujarat","overall_cd_ratio":"35.05","total_deposit":"355821.23","total_advance":"124701.52","total_branch":"84"},{"district":"Tengnoupal","state":"manipur","overall_cd_ratio":"101"},{"district":"Thoubal","state":"manipur","overall_cd_ratio":"70"},{"district":"Tinsukia","state":"assam","overall_cd_ratio":"51.48"},{"district":"Udalguri","state":"assam","overall_cd_ratio":"72.3"},{"district":"Ukhrul","state":"manipur","overall_cd_ratio":"47"},{"district":"Unakoti","state":"tripura","overall_cd_ratio":"72.0","total_deposit":"91510.86","total_advance":"65811.52","total_branch":"33.0"},{"district":"Vadodara","state":"gujarat","overall_cd_ratio":"71.55","total_deposit":"8842540.77","total_advance":"6327061.18","total_branch":"743"},{"district":"Valsad","state":"gujarat","overall_cd_ratio":"66.22","total_deposit":"1742977.03","total_advance":"1154152.74","total_branch":"271"},{"district":"Visakhapatanam","state":"andhra-pradesh","overall_cd_ratio":"118.06"},{"district":"Vizianagaram","state":"andhra-pradesh","overall_cd_ratio":"91.18"},{"district":"West Godavari","state":"andhra-pradesh","overall_cd_ratio":"145.22"},{"district":"West Karbi Anglong","state":"assam","overall_cd_ratio":"74.43"},{"district":"West Tripura","state":"tripura","overall_cd_ratio":"49.0","total_deposit":"1786727.19","total_advance":"881563.77","total_branch":"194.0"},{"district":"Y.s.r.","state":"andhra-pradesh","overall_cd_ratio":"124.09"},{"district":"Yamunanagar","state":"haryana","overall_cd_ratio":"61.1","total_deposit":"1318330.0","total_advance":"805479.0"}]}